{
  "Token": {
    "UID": "c20aa444-c23b-4081-843a-baf59b598ca6",
    "Name": "LocationStates"
  },
  "Type": 3,
  "Options": [
    {
      "Token": {
        "UID": "bab89c01-699a-4023-b4c1-69f6142755ad",
        "Name": "InitLoc1"
      },
      "AdditionalData": ""
    },
    {
      "Token": {
        "UID": "5b059820-26d2-4463-88e5-a224a93f3735",
        "Name": "OreProducing"
      },
      "AdditionalData": ""
    },
    {
      "Token": {
        "UID": "00252ffd-4a1f-478b-b834-7b37fa2c5ce4",
        "Name": "OreProcessing"
      },
      "AdditionalData": ""
    }
  ]
}